LICENSE
MANIFEST.in
README
setup.cfg
setup.py
sphinxcontrib/__init__.py
sphinxcontrib/osaka.py
sphinxcontrib_osaka.egg-info/PKG-INFO
sphinxcontrib_osaka.egg-info/SOURCES.txt
sphinxcontrib_osaka.egg-info/dependency_links.txt
sphinxcontrib_osaka.egg-info/namespace_packages.txt
sphinxcontrib_osaka.egg-info/not-zip-safe
sphinxcontrib_osaka.egg-info/requires.txt
sphinxcontrib_osaka.egg-info/top_level.txt