Metadata-Version: 1.0
Name: sphinxcontrib-osaka
Version: 0.1dev-20100410
Summary: Sphinx extension osaka
Home-page: http://bitbucket.org/birkenfeld/sphinx-contrib
Author: SHIBUKAWA Yoshiki
Author-email: yoshiki at shibu.jp
License: BSD
Download-URL: http://pypi.python.org/pypi/sphinxcontrib-osaka
Platform: any
Classifier: Development Status :: 4 - Beta
Classifier: Environment :: Console
Classifier: Environment :: Web Environment
Classifier: Intended Audience :: Developers
Classifier: License :: OSI Approved :: BSD License
Classifier: Natural Language :: Japanese
Classifier: Operating System :: OS Independent
Classifier: Programming Language :: Python
Classifier: Topic :: Documentation
Classifier: Topic :: Utilities
Classifier: Topic :: Text Processing :: Filters
Classifier: Topic :: Text Processing :: Linguistic
